ALU_4_bit.srcs/sources_1/new/ALU_4_bit_Pipeline.v
`timescale 1ns / 1ps

module ALU_4_bit_Pipeline (
    input clk, rst,
    input [3:0] A, B,
    input [3:0] sel,
    
    output [7:0] result,
    output zero_flag, overflow_flag, div_by_zero_flag
);
    
//  stage - 1: Input Registers
  reg [3:0] A_r, B_r;
  reg [3:0] sel_r;
  
//  Implementation
  always@(posedge clk or posedge rst) begin
    if(rst) begin
        A_r   <= 0;
        B_r   <= 0;
        sel_r <= 0;
    end
    else begin
        A_r   <= A;
        B_r   <= B;
        sel_r <= sel;
    end
  end
  
  
//  stage - 2: Execution
  reg [7:0] alu_out;
  reg ovf_flag, dbz_flag;
  
//  Implementation
  always@(*) begin
    
    alu_out  = 0;
    ovf_flag = 0;
    dbz_flag = 0;
    
    case(sel_r)
    
        4'b0000 : begin
                  alu_out         =  A_r + B_r;   // addition
                  ovf_flag = (A_r + B_r > 8'd15);
                  end
                  
        4'b0001 : begin
                  alu_out         =  A_r - B_r;   // subtraction
                  ovf_flag = (A_r < B_r);
                  end
                  
        4'b0010 : begin
                  alu_out         =  A_r * B_r;   // multipication
                  ovf_flag = (A_r * B_r > 8'd255);
                  end
                  
        4'b0011 : begin
                    if(B_r == 0) begin
                        alu_out = 8'hFF;
                        dbz_flag = 1;
                    end else 
                    begin
                        alu_out = A_r / B_r;
                    end                      
                  end  
                  
        4'b0100 : alu_out = {4'b0,  (A_r & B_r)};  // and
        4'b0101 : alu_out = {4'b0,  (A_r | B_r)};  // or
        4'b0110 : alu_out = {4'b0, ~(A_r & B_r)};  // nand
        4'b0111 : alu_out = {4'b0, ~(A_r | B_r)};  // nor
        4'b1000 : alu_out = {4'b0,  (A_r ^ B_r)};  // xor
        4'b1001 : alu_out = {4'b0, ~(A_r ^ B_r)};  // xnor
        
        default : alu_out = 0; 
        
    endcase
end

//  Stage - 3: Register write back
reg [7:0] result_r3;
reg zero_flag_r3, overflow_flag_r3, div_by_zero_flag_r3;

always@(posedge clk or posedge rst) begin

    if(rst) begin
    
        result_r3 <= 0;
        zero_flag_r3 <= 0;
        overflow_flag_r3 <= 0;
        div_by_zero_flag_r3 <= 0;
        
    end else begin
    
        result_r3 <= alu_out;
        zero_flag_r3 <= (alu_out == 0);
        overflow_flag_r3 <= ovf_flag;
        div_by_zero_flag_r3 <= dbz_flag;
        
    end

end

//  Final Result
assign result = result_r3;
assign zero_flag = zero_flag_r3;
assign overflow_flag = overflow_flag_r3;
assign div_by_zero_flag = div_by_zero_flag_r3;
    
endmodule

ALU_4_bit.srcs/sim_1/new/ALU_Pipeline_tb.v
`timescale 1ns / 1ps

module ALU_Pipeline_tb;
    
    reg clk, rst;
    reg [3:0] A, B;
    reg [3:0] sel;
    
    wire [7:0] result;
    wire zero_flag, overflow_flag, div_by_zero_flag;
    
    reg [63:0] op_name; // operation name    
    
    ALU_4_bit_Pipeline alu1(
        .clk(clk),
        .rst(rst),
        .A(A),
        .B(B),
        .sel(sel),
        .result(result),
        .zero_flag(zero_flag),
        .overflow_flag(overflow_flag),
        .div_by_zero_flag(div_by_zero_flag) );
    
    always #2 clk = ~clk;
    
//    operation name decoder
    always@(*) begin
        case(sel)
            4'b0000 : op_name = "ADD";
            4'b0001 : op_name = "SUB";
            4'b0010 : op_name = "MUL";
            4'b0011 : op_name = "DIV";
            4'b0100 : op_name = "AND";
            4'b0101 : op_name = "OR";
            4'b0110 : op_name = "NAND";
            4'b0111 : op_name = "NOR";
            4'b1000 : op_name = "XOR";
            4'b1001 : op_name = "XNOR";
            default : op_name = "UNKNOWN";
        endcase
    end
    
    integer i, j, s;
    
//    main test cases
    initial begin
    
        $dumpfile("alu_pipelined.vcd");
        $dumpvars(0, ALU_Pipeline_tb);
    
        clk = 0;
        rst = 1;
        A   = 0;
        B   = 0;
        sel = 0;
        
        #5;
        rst = 0;
        
        repeat(3) @(posedge clk);
        
//      loop for all combination
        for(s = 0; s <= 9; s = s + 1) begin
            sel = s;
            
//          loop for all A and B combinations
            for(i = 0; i <= 15; i = i + 1) begin
                for(j = 0; j <= 15; j = j + 1) begin
                    A = i;
                    B = j;
                    
                    repeat(3) @(posedge clk);
                    
                    $display("T=%0t | OP=%s | A=%0d | B=%0d | Result=%0d | Z=%b | OF=%b | DBZ=%b",
         $time, op_name, A, B, result, zero_flag, overflow_flag, div_by_zero_flag);

                end
            end
                    
        end
        
        #100;
        $finish;
        
    end
               
endmodule

ALU_4_bit.sim/sim_1/behav/xsim/alu_pipelined.vcd
$date
   Sun Mar 29 09:56:59 2026
$end
$version
  2018.3
$end
$timescale
  1ps
$end
$scope module ALU_Pipeline_tb $end
$var reg 1 ! clk $end
$var reg 1 " rst $end
$var reg 4 # A [3:0] $end
$var reg 4 $ B [3:0] $end
$var reg 4 % sel [3:0] $end
$var wire 8 & result [7:0] $end
$var wire 1 ' zero_flag $end
$var wire 1 ( overflow_flag $end
$var wire 1 ) div_by_zero_flag $end
$var reg 64 * op_name [63:0] $end
$var integer 32 + i $end
$var integer 32 , j $end
$var integer 32 - s $end
$scope module alu1 $end
$var wire 1 . clk $end
$var wire 1 / rst $end
$var wire 4 0 A [3:0] $end
$var wire 4 1 B [3:0] $end
$var wire 4 2 sel [3:0] $end
$var wire 8 & result [7:0] $end
$var wire 1 ' zero_flag $end
$var wire 1 ( overflow_flag $end
$var wire 1 ) div_by_zero_flag $end
$var reg 4 3 A_r [3:0] $end
$var reg 4 4 B_r [3:0] $end
$var reg 4 5 sel_r [3:0] $end
$var reg 8 6 alu_out [7:0] $end
$var reg 1 7 ovf_flag $end
$var reg 1 8 dbz_flag $end
$var reg 8 9 result_r3 [7:0] $end
$var reg 1 : zero_flag_r3 $end
$var reg 1 ; overflow_flag_r3 $end
$var reg 1 < div_by_zero_flag_r3 $end
$upscope $end
$upscope $end
$enddefinitions $end
#0
$dumpvars
0!
1"
b0 #
b0 $
b0 %
b0 &
0'
0(
0)
b10000010100010001000100 *
bx +
bx ,
bx -
0.
1/
b0 0
b0 1
b0 2
b0 3
b0 4
b0 5
b0 6
07
08
b0 9
0:
0;
0<
$end
#2000
1!
1.
#4000
0!
0.
#5000
0"
0/
#6000
1!
1'
1.
1:
#8000
0!
0.
#10000
1!
1.
#12000
0!
0.
#14000
1!
b0 #
b0 $
b0 %
b0 +
b0 ,
b0 -
1.
#16000
0!
0.
#18000
1!
1.
#20000
0!
0.
#22000
1!
1.
#24000
0!
0.
#26000
1!
b0 #
b1 $
b1 ,
1.
b1 1
b1 4
b1 6
#28000
0!
0.
#30000
1!
b1 &
0'
1.
b1 9
0:
#32000
0!
0.
#34000
1!
1.
#36000
0!
0.
#38000
1!
b0 #
b10 $
b10 ,
1.
b10 1
b10 4
b10 6
#40000
0!
0.
#42000
1!
b10 &
1.
b10 9
#44000
0!
0.
#46000
1!
1.
#48000
0!
0.
#50000
1!
b0 #
b11 $
b11 ,
1.
b11 1
b11 4
b11 6
#52000
0!
0.
#54000
1!
b11 &
1.
b11 9
#56000
0!
0.
#58000
1!
1.
#60000
0!
0.
#62000
1!
b0 #
b100 $
b100 ,
1.
b100 1
b100 4
b100 6
#64000
0!
0.
#66000
1!
b100 &
1.
b100 9
#68000
0!
0.
#70000
1!
1.
#72000
0!
0.
#74000
1!
b0 #
b101 $
b101 ,
1.
b101 1
b101 4
b101 6
#76000
0!
0.
#78000
1!
b101 &
1.
b101 9
#80000
0!
0.
#82000
1!
1.
#84000
0!
0.
#86000
1!
b0 #
b110 $
b110 ,
1.
b110 1
b110 4
b110 6
#88000
0!
0.
#90000
1!
b110 &
1.
b110 9
#92000
0!
0.
#94000
1!
1.
#96000
0!
0.
#98000
1!
b0 #
b111 $
b111 ,
1.
b111 1
b111 4
b111 6
#100000
0!
0.
#102000
1!
b111 &
1.
b111 9
#104000
0!
0.
#106000
1!
1.
#108000
0!
0.
#110000
1!
b0 #
b1000 $
b1000 ,
1.
b1000 1
b1000 4
b1000 6
#112000
0!
0.
#114000
1!
b1000 &
1.
b1000 9
#116000
0!
0.
#118000
1!
1.
#120000
0!
0.
#122000
1!
b0 #
b1001 $
b1001 ,
1.
b1001 1
b1001 4
b1001 6
#124000
0!
0.
#126000
1!
b1001 &
1.
b1001 9
#128000
0!
0.
#130000
1!
1.
#132000
0!
0.
#134000
1!
b0 #
b1010 $
b1010 ,
1.
b1010 1
b1010 4
b1010 6
#136000
0!
0.
#138000
1!
b1010 &
1.
b1010 9
#140000
0!
0.
#142000
1!
1.
#144000
0!
0.
#146000
1!
b0 #
b1011 $
b1011 ,
1.
b1011 1
b1011 4
b1011 6
#148000
0!
0.
#150000
1!
b1011 &
1.
b1011 9
#152000
0!
0.
#154000
1!
1.
#156000
0!
0.
#158000
1!
b0 #
b1100 $
b1100 ,
1.
b1100 1
b1100 4
b1100 6
#160000
0!
0.
#162000
1!
b1100 &
1.
b1100 9
#164000
0!
0.
#166000
1!
1.
#168000
0!
0.
#170000
1!
b0 #
b1101 $
b1101 ,
1.
b1101 1
b1101 4
b1101 6
#172000
0!
0.
#174000
1!
b1101 &
1.
b1101 9
#176000
0!
0.
#178000
1!
1.
#180000
0!
0.
#182000
1!
b0 #
b1110 $
b1110 ,
1.
b1110 1
b1110 4
b1110 6
#184000
0!
0.
#186000
1!
b1110 &
1.
b1110 9
#188000
0!
0.
#190000
1!
1.
#192000
0!
0.
#194000
1!
b0 #
b1111 $
b1111 ,
1.
b1111 1
b1111 4
b1111 6
#196000
0!
0.
#198000
1!
b1111 &
1.
b1111 9
#200000
0!
0.
#202000
1!
1.
#204000
0!
0.
#206000
1!
b1 #
b0 $
b1 +
b0 ,
1.
b1 0
b0 1
b1 3
b0 4
b1 6
#208000
0!
0.
#210000
1!
b1 &
1.
b1 9
#212000
0!
0.
#214000
1!
1.
#216000
0!
0.
#218000
1!
b1 #
b1 $
b1 ,
1.
b1 1
b1 4
b10 6
#220000
0!
0.
#222000
1!
b10 &
1.
b10 9
#224000
0!
0.
#226000
1!
1.
#228000
0!
0.
#230000
1!
b1 #
b10 $
b10 ,
1.
b10 1
b10 4
b11 6
#232000
0!
0.
#234000
1!
b11 &
1.
b11 9
#236000
0!
0.
#238000
1!
1.
#240000
0!
0.
#242000
1!
b1 #
b11 $
b11 ,
1.
b11 1
b11 4
b100 6
#244000
0!
0.
#246000
1!
b100 &
1.
b100 9
#248000
0!
0.
#250000
1!
1.
#252000
0!
0.
#254000
1!
b1 #
b100 $
b100 ,
1.
b100 1
b100 4
b101 6
#256000
0!
0.
#258000
1!
b101 &
1.
b101 9
#260000
0!
0.
#262000
1!
1.
#264000
0!
0.
#266000
1!
b1 #
b101 $
b101 ,
1.
b101 1
b101 4
b110 6
#268000
0!
0.
#270000
1!
b110 &
1.
b110 9
#272000
0!
0.
#274000
1!
1.
#276000
0!
0.
#278000
1!
b1 #
b110 $
b110 ,
1.
b110 1
b110 4
b111 6
#280000
0!
0.
#282000
1!
b111 &
1.
b111 9
#284000
0!
0.
#286000
1!
1.
#288000
0!
0.
#290000
1!
b1 #
b111 $
b111 ,
1.
b111 1
b111 4
b1000 6
#292000
0!
0.
#294000
1!
b1000 &
1.
b1000 9
#296000
0!
0.
#298000
1!
1.
#300000
0!
0.
#302000
1!
b1 #
b1000 $
b1000 ,
1.
b1000 1
b1000 4
b1001 6
#304000
0!
0.
#306000
1!
b1001 &
1.
b1001 9
#308000
0!
0.
#310000
1!
1.
#312000
0!
0.
#314000
1!
b1 #
b1001 $
b1001 ,
1.
b1001 1
b1001 4
b1010 6
#316000
0!
0.
#318000
1!
b1010 &
1.
b1010 9
#320000
0!
0.
#322000
1!
1.
#324000
0!
0.
#326000
1!
b1 #
b1010 $
b1010 ,
1.
b1010 1
b1010 4
b1011 6
#328000
0!
0.
#330000
1!
b1011 &
1.
b1011 9
#332000
0!
0.
#334000
1!
1.
#336000
0!
0.
#338000
1!
b1 #
b1011 $
b1011 ,
1.
b1011 1
b1011 4
b1100 6
#340000
0!
0.
#342000
1!
b1100 &
1.
b1100 9
#344000
0!
0.
#346000
1!
1.
#348000
0!
0.
#350000
1!
b1 #
b1100 $
b1100 ,
1.
b1100 1
b1100 4
b1101 6
#352000
0!
0.
#354000
1!
b1101 &
1.
b1101 9
#356000
0!
0.
#358000
1!
1.
#360000
0!
0.
#362000
1!
b1 #
b1101 $
b1101 ,
1.
b1101 1
b1101 4
b1110 6
#364000
0!
0.
#366000
1!
b1110 &
1.
b1110 9
#368000
0!
0.
#370000
1!
1.
#372000
0!
0.
#374000
1!
b1 #
b1110 $
b1110 ,
1.
b1110 1
b1110 4
b1111 6
#376000
0!
0.
#378000
1!
b1111 &
1.
b1111 9
#380000
0!
0.
#382000
1!
1.
#384000
0!
0.
#386000
1!
b1 #
b1111 $
b1111 ,
1.
b1111 1
b1111 4
b10000 6
17
#388000
0!
0.
#390000
1!
b10000 &
1(
1.
b10000 9
1;
#392000
0!
0.
#394000
1!
1.
#396000
0!
0.
#398000
1!
b10 #
b0 $
b10 +
b0 ,
1.
b10 0
b0 1
b10 3
b0 4
b10 6
07
#400000
0!
0.
#402000
1!
b10 &
0(
1.
b10 9
0;
#404000
0!
0.
#406000
1!
1.
#408000
0!
0.
#410000
1!
b10 #
b1 $
b1 ,
1.
b1 1
b1 4
b11 6
#412000
0!
0.
#414000
1!
b11 &
1.
b11 9
#416000
0!
0.
#418000
1!
1.
#420000
0!
0.
#422000
1!
b10 #
b10 $
b10 ,
1.
b10 1
b10 4
b100 6
#424000
0!
0.
#426000
1!
b100 &
1.
b100 9
#428000
0!
0.
#430000
1!
1.
#432000
0!
0.
#434000
1!
b10 #
b11 $
b11 ,
1.
b11 1
b11 4
b101 6
#436000
0!
0.
#438000
1!
b101 &
1.
b101 9
#440000
0!
0.
#442000
1!
1.
#444000
0!
0.
#446000
1!
b10 #
b100 $
b100 ,
1.
b100 1
b100 4
b110 6
#448000
0!
0.
#450000
1!
b110 &
1.
b110 9
#452000
0!
0.
#454000
1!
1.
#456000
0!
0.
#458000
1!
b10 #
b101 $
b101 ,
1.
b101 1
b101 4
b111 6
#460000
0!
0.
#462000
1!
b111 &
1.
b111 9
#464000
0!
0.
#466000
1!
1.
#468000
0!
0.
#470000
1!
b10 #
b110 $
b110 ,
1.
b110 1
b110 4
b1000 6
#472000
0!
0.
#474000
1!
b1000 &
1.
b1000 9
#476000
0!
0.
#478000
1!
1.
#480000
0!
0.
#482000
1!
b10 #
b111 $
b111 ,
1.
b111 1
b111 4
b1001 6
#484000
0!
0.
#486000
1!
b1001 &
1.
b1001 9
#488000
0!
0.
#490000
1!
1.
#492000
0!
0.
#494000
1!
b10 #
b1000 $
b1000 ,
1.
b1000 1
b1000 4
b1010 6
#496000
0!
0.
#498000
1!
b1010 &
1.
b1010 9
#500000
0!
0.
#502000
1!
1.
#504000
0!
0.
#506000
1!
b10 #
b1001 $
b1001 ,
1.
b1001 1
b1001 4
b1011 6
#508000
0!
0.
#510000
1!
b1011 &
1.
b1011 9
#512000
0!
0.
#514000
1!
1.
#516000
0!
0.
#518000
1!
b10 #
b1010 $
b1010 ,
1.
b1010 1
b1010 4
b1100 6
#520000
0!
0.
#522000
1!
b1100 &
1.
b1100 9
#524000
0!
0.
#526000
1!
1.
#528000
0!
0.
#530000
1!
b10 #
b1011 $
b1011 ,
1.
b1011 1
b1011 4
b1101 6
#532000
0!
0.
#534000
1!
b1101 &
1.
b1101 9
#536000
0!
0.
#538000
1!
1.
#540000
0!
0.
#542000
1!
b10 #
b1100 $
b1100 ,
1.
b1100 1
b1100 4
b1110 6
#544000
0!
0.
#546000
1!
b1110 &
1.
b1110 9
#548000
0!
0.
#550000
1!
1.
#552000
0!
0.
#554000
1!
b10 #
b1101 $
b1101 ,
1.
b1101 1
b1101 4
b1111 6
#556000
0!
0.
#558000
1!
b1111 &
1.
b1111 9
#560000
0!
0.
#562000
1!
1.
#564000
0!
0.
#566000
1!
b10 #
b1110 $
b1110 ,
1.
b1110 1
b1110 4
b10000 6
17
#568000
0!
0.
#570000
1!
b10000 &
1(
1.
b10000 9
1;
#572000
0!
0.
#574000
1!
1.
#576000
0!
0.
#578000
1!
b10 #
b1111 $
b1111 ,
1.
b1111 1
b1111 4
b10001 6
17
#580000
0!
0.
#582000
1!
b10001 &
1.
b10001 9
#584000
0!
0.
#586000
1!
1.
#588000
0!
0.
#590000
1!
b11 #
b0 $
b11 +
b0 ,
1.
b11 0
b0 1
b11 3
b0 4
b11 6
07
#592000
0!
0.
#594000
1!
b11 &
0(
1.
b11 9
0;
#596000
0!
0.
#598000
1!
1.
#600000
0!
0.
#602000
1!
b11 #
b1 $
b1 ,
1.
b1 1
b1 4
b100 6
#604000
0!
0.
#606000
1!
b100 &
1.
b100 9
#608000
0!
0.
#610000
1!
1.
#612000
0!
0.
#614000
1!
b11 #
b10 $
b10 ,
1.
b10 1
b10 4
b101 6
#616000
0!
0.
#618000
1!
b101 &
1.
b101 9
#620000
0!
0.
#622000
1!
1.
#624000
0!
0.
#626000
1!
b11 #
b11 $
b11 ,
1.
b11 1
b11 4
b110 6
#628000
0!
0.
#630000
1!
b110 &
1.
b110 9
#632000
0!
0.
#634000
1!
1.
#636000
0!
0.
#638000
1!
b11 #
b100 $
b100 ,
1.
b100 1
b100 4
b111 6
#640000
0!
0.
#642000
1!
b111 &
1.
b111 9
#644000
0!
0.
#646000
1!
1.
#648000
0!
0.
#650000
1!
b11 #
b101 $
b101 ,
1.
b101 1
b101 4
b1000 6
#652000
0!
0.
#654000
1!
b1000 &
1.
b1000 9
#656000
0!
0.
#658000
1!
1.
#660000
0!
0.
#662000
1!
b11 #
b110 $
b110 ,
1.
b110 1
b110 4
b1001 6
#664000
0!
0.
#666000
1!
b1001 &
1.
b1001 9
#668000
0!
0.
#670000
1!
1.
#672000
0!
0.
#674000
1!
b11 #
b111 $
b111 ,
1.
b111 1
b111 4
b1010 6
#676000
0!
0.
#678000
1!
b1010 &
1.
b1010 9
#680000
0!
0.
#682000
1!
1.
#684000
0!
0.
#686000
1!
b11 #
b1000 $
b1000 ,
1.
b1000 1
b1000 4
b1011 6
#688000
0!
0.
#690000
1!
b1011 &
1.
b1011 9
#692000
0!
0.
#694000
1!
1.
#696000
0!
0.
#698000
1!
b11 #
b1001 $
b1001 ,
1.
b1001 1
b1001 4
b1100 6
#700000
0!
0.
#702000
1!
b1100 &
1.
b1100 9
#704000
0!
0.
#706000
1!
1.
#708000
0!
0.
#710000
1!
b11 #
b1010 $
b1010 ,
1.
b1010 1
b1010 4
b1101 6
#712000
0!
0.
#714000
1!
b1101 &
1.
b1101 9
#716000
0!
0.
#718000
1!
1.
#720000
0!
0.
#722000
1!
b11 #
b1011 $
b1011 ,
1.
b1011 1
b1011 4
b1110 6
#724000
0!
0.
#726000
1!
b1110 &
1.
b1110 9
#728000
0!
0.
#730000
1!
1.
#732000
0!
0.
#734000
1!
b11 #
b1100 $
b1100 ,
1.
b1100 1
b1100 4
b1111 6
#736000
0!
0.
#738000
1!
b1111 &
1.
b1111 9
#740000
0!
0.
#742000
1!
1.
#744000
0!
0.
#746000
1!
b11 #
b1101 $
b1101 ,
1.
b1101 1
b1101 4
b10000 6
17
#748000
0!
0.
#750000
1!
b10000 &
1(
1.
b10000 9
1;
#752000
0!
0.
#754000
1!
1.
#756000
0!
0.
#758000
1!
b11 #
b1110 $
b1110 ,
1.
b1110 1
b1110 4
b10001 6
17
#760000
0!
0.
#762000
1!
b10001 &
1.
b10001 9
#764000
0!
0.
#766000
1!
1.
#768000
0!
0.
#770000
1!
b11 #
b1111 $
b1111 ,
1.
b1111 1
b1111 4
b10010 6
17
#772000
0!
0.
#774000
1!
b10010 &
1.
b10010 9
#776000
0!
0.
#778000
1!
1.
#780000
0!
0.
#782000
1!
b100 #
b0 $
b100 +
b0 ,
1.
b100 0
b0 1
b100 3
b0 4
b100 6
07
#784000
0!
0.
#786000
1!
b100 &
0(
1.
b100 9
0;
#788000
0!
0.
#790000
1!
1.
#792000
0!
0.
#794000
1!
b100 #
b1 $
b1 ,
1.
b1 1
b1 4
b101 6
#796000
0!
0.
#798000
1!
b101 &
1.
b101 9
#800000
0!
0.
#802000
1!
1.
#804000
0!
0.
#806000
1!
b100 #
b10 $
b10 ,
1.
b10 1
b10 4
b110 6
#808000
0!
0.
#810000
1!
b110 &
1.
b110 9
#812000
0!
0.
#814000
1!
1.
#816000
0!
0.
#818000
1!
b100 #
b11 $
b11 ,
1.
b11 1
b11 4
b111 6
#820000
0!
0.
#822000
1!
b111 &
1.
b111 9
#824000
0!
0.
#826000
1!
1.
#828000
0!
0.
#830000
1!
b100 #
b100 $
b100 ,
1.
b100 1
b100 4
b1000 6
#832000
0!
0.
#834000
1!
b1000 &
1.
b1000 9
#836000
0!
0.
#838000
1!
1.
#840000
0!
0.
#842000
1!
b100 #
b101 $
b101 ,
1.
b101 1
b101 4
b1001 6
#844000
0!
0.
#846000
1!
b1001 &
1.
b1001 9
#848000
0!
0.
#850000
1!
1.
#852000
0!
0.
#854000
1!
b100 #
b110 $
b110 ,
1.
b110 1
b110 4
b1010 6
#856000
0!
0.
#858000
1!
b1010 &
1.
b1010 9
#860000
0!
0.
#862000
1!
1.
#864000
0!
0.
#866000
1!
b100 #
b111 $
b111 ,
1.
b111 1
b111 4
b1011 6
#868000
0!
0.
#870000
1!
b1011 &
1.
b1011 9
#872000
0!
0.
#874000
1!
1.
#876000
0!
0.
#878000
1!
b100 #
b1000 $
b1000 ,
1.
b1000 1
b1000 4
b1100 6
#880000
0!
0.
#882000
1!
b1100 &
1.
b1100 9
#884000
0!
0.
#886000
1!
1.
#888000
0!
0.
#890000
1!
b100 #
b1001 $
b1001 ,
1.
b1001 1
b1001 4
b1101 6
#892000
0!
0.
#894000
1!
b1101 &
1.
b1101 9
#896000
0!
0.
#898000
1!
1.
#900000
0!
0.
#902000
1!
b100 #
b1010 $
b1010 ,
1.
b1010 1
b1010 4
b1110 6
#904000
0!
0.
#906000
1!
b1110 &
1.
b1110 9
#908000
0!
0.
#910000
1!
1.
#912000
0!
0.
#914000
1!
b100 #
b1011 $
b1011 ,
1.
b1011 1
b1011 4
b1111 6
#916000
0!
0.
#918000
1!
b1111 &
1.
b1111 9
#920000
0!
0.
#922000
1!
1.
#924000
0!
0.
#926000
1!
b100 #
b1100 $
b1100 ,
1.
b1100 1
b1100 4
b10000 6
17
#928000
0!
0.
#930000
1!
b10000 &
1(
1.
b10000 9
1;
#932000
0!
0.
#934000
1!
1.
#936000
0!
0.
#938000
1!
b100 #
b1101 $
b1101 ,
1.
b1101 1
b1101 4
b10001 6
17
#940000
0!
0.
#942000
1!
b10001 &
1.
b10001 9
#944000
0!
0.
#946000
1!
1.
#948000
0!
0.
#950000
1!
b100 #
b1110 $
b1110 ,
1.
b1110 1
b1110 4
b10010 6
17
#952000
0!
0.
#954000
1!
b10010 &
1.
b10010 9
#956000
0!
0.
#958000
1!
1.
#960000
0!
0.
#962000
1!
b100 #
b1111 $
b1111 ,
1.
b1111 1
b1111 4
b10011 6
17
#964000
0!
0.
#966000
1!
b10011 &
1.
b10011 9
#968000
0!
0.
#970000
1!
1.
#972000
0!
0.
#974000
1!
b101 #
b0 $
b101 +
b0 ,
1.
b101 0
b0 1
b101 3
b0 4
b101 6
07
#976000
0!
0.
#978000
1!
b101 &
0(
1.
b101 9
0;
#980000
0!
0.
#982000
1!
1.
#984000
0!
0.
#986000
1!
b101 #
b1 $
b1 ,
1.
b1 1
b1 4
b110 6
#988000
0!
0.
#990000
1!
b110 &
1.
b110 9
#992000
0!
0.
#994000
1!
1.
#996000
0!
0.
#998000
1!
b101 #
b10 $
b10 ,
1.
b10 1
b10 4
b111 6
